pcap_summary/__init__.py
pcap_summary/pcap_summary.py
pcap_summary-1.0.0.dist-info/METADATA
pcap_summary-1.0.0.dist-info/WHEEL
pcap_summary-1.0.0.dist-info/entry_points.txt
pcap_summary-1.0.0.dist-info/top_level.txt
pcap_summary-1.0.0.dist-info/RECORD
