Metadata-Version: 2.1
Name: pcap-summary
Version: 1.0.0
Summary: Scapy wrapper for summarizing PCAP flows
Author-email: Craig ARMSTRONG <cag@izec.fr>
Project-URL: Homepage, https://github.com/craigarms/pcap_summary
Keywords: scapy,pcap,summary
Classifier: Programming Language :: Python
Classifier: Programming Language :: Python :: 3
Requires-Python: >=3.7
Requires-Dist: scapy (>=2.4.5)
Requires-Dist: tabulate (>=0.9.0)
Provides-Extra: dev
Requires-Dist: black ; extra == 'dev'
Requires-Dist: bumpver ; extra == 'dev'
Requires-Dist: isort ; extra == 'dev'
Requires-Dist: pip-tools ; extra == 'dev'
Requires-Dist: pytest ; extra == 'dev'
